ringcentral_client/__init__.py
ringcentral_client/rest_client.py
ringcentral_client-0.8.0.dist-info/METADATA
ringcentral_client-0.8.0.dist-info/WHEEL
ringcentral_client-0.8.0.dist-info/top_level.txt
ringcentral_client-0.8.0.dist-info/RECORD
